toolfront/__init__.py
toolfront/application.py
toolfront/main.py
toolfront/utils.py
toolfront/cli/__init__.py
toolfront/cli/delete.py
toolfront/cli/deploy.py
toolfront/cli/list.py
toolfront/cli/mcp.py
toolfront/cli/serve.py
toolfront/cli/update.py
toolfront/lib/__init__.py
toolfront/lib/gateway.py
toolfront-0.4.1.dist-info/licenses/LICENSE
toolfront-0.4.1.dist-info/METADATA
toolfront-0.4.1.dist-info/WHEEL
toolfront-0.4.1.dist-info/entry_points.txt
toolfront-0.4.1.dist-info/top_level.txt
toolfront-0.4.1.dist-info/RECORD
