Metadata-Version: 2.4
Name: toolfront
Version: 0.4.1
Summary: Build AI applications in Markdown.
Author-email: Esteban Safranchik <esteban@statespace.com>, Gavin Chan <gavin@statespace.com>
License: MIT
Project-URL: Homepage, https://github.com/statespace-tech/toolfront
Project-URL: Repository, https://github.com/statespace-tech/toolfront
Project-URL: Documentation, https://docs.toolfront.ai
Project-URL: Bug Tracker, https://github.com/statespace-tech/toolfront/issues
Classifier: License :: OSI Approved :: MIT License
Classifier: Programming Language :: Python
Classifier: Programming Language :: Python :: 3
Classifier: Programming Language :: Python :: 3 :: Only
Classifier: Operating System :: OS Independent
Requires-Python: >=3.10
License-File: LICENSE
Requires-Dist: click>=8.2.1
Requires-Dist: fastapi>=0.120.0
Requires-Dist: httpx>=0.28.1
Requires-Dist: mcp[cli]>=1.18.0
Requires-Dist: pydantic>=2.12.3
Requires-Dist: pydantic-ai-slim[anthropic,bedrock,cohere,google,groq,huggingface,mistral,openai,vertexai]>=1.1.0
Requires-Dist: pytest>=8.4.1
Requires-Dist: rich>=14.1.0
Requires-Dist: tabulate>=0.9.0
Provides-Extra: test
Requires-Dist: pytest>=7.0.0; extra == "test"
Requires-Dist: pytest-asyncio>=0.21.0; extra == "test"
Requires-Dist: pytest-httpx>=0.30.0; extra == "test"
Provides-Extra: dev
Requires-Dist: pre-commit>=3.0.0; extra == "dev"
Requires-Dist: ruff>=0.1.0; extra == "dev"
Requires-Dist: mkdocs-material[imaging]>=9.6.16; extra == "dev"
Requires-Dist: mkdocstrings[python]>=0.30.0; extra == "dev"
Dynamic: license-file
